ufcpredictor/__init__.py
ufcpredictor/app.py
ufcpredictor/data_aggregator.py
ufcpredictor/data_enhancers.py
ufcpredictor/data_processor.py
ufcpredictor/datasets.py
ufcpredictor/loss_functions.py
ufcpredictor/models.py
ufcpredictor/optimizers.py
ufcpredictor/plot_tools.py
ufcpredictor/pretrained_models/simple_app_model.pt
ufcpredictor/pretrained_models/ufc_fight_net_with_time_evolution.pt
ufcpredictor/schedulers.py
ufcpredictor/trainer.py
ufcpredictor/ufcpredictor.py
ufcpredictor/utils.py
ufcpredictor/utils_sheets.py
ufcpredictor-1.2.2.dist-info/METADATA
ufcpredictor-1.2.2.dist-info/WHEEL
ufcpredictor-1.2.2.dist-info/entry_points.txt
ufcpredictor-1.2.2.dist-info/RECORD
