Metadata-Version: 2.3
Name: ufcpredictor
Version: 1.2.2
Summary: A simple predictor for UFC fights
Author: César Ramírez-Pérez
Requires-Python: >=3.10,<4
Classifier: Programming Language :: Python :: 3
Classifier: Programming Language :: Python :: 3.10
Classifier: Programming Language :: Python :: 3.11
Classifier: Programming Language :: Python :: 3.12
Classifier: Programming Language :: Python :: 3.13
Requires-Dist: fuzzywuzzy (>=0.18.0,<0.19.0)
Requires-Dist: google-api-python-client (>=2.176.0,<3.0.0)
Requires-Dist: google-auth-oauthlib (>=1.2.2,<2.0.0)
Requires-Dist: gradio (>=5.6.0,<6.0.0)
Requires-Dist: huggingface-hub (>=0.26.2,<0.27.0)
Requires-Dist: importlib-resources (>=6.5.2,<7.0.0)
Requires-Dist: matplotlib (>=3.9.2,<4.0.0)
Requires-Dist: mlflow (>=2.18.0,<3.0.0)
Requires-Dist: numpy (>=2.1.3,<3.0.0)
Requires-Dist: pandas (>=2.2.3,<3.0.0)
Requires-Dist: scikit-learn (>=1.5.2,<2.0.0)
Requires-Dist: torch (>=2.5.1,<3.0.0)
Requires-Dist: tqdm (>=4.67.0,<5.0.0)
Requires-Dist: ufcscraper (>=0.2.0,<0.3.0)
